astropandas/__init__.py
astropandas/io.py
astropandas/match.py
astropandas-1.2.2.dist-info/LICENSE
astropandas-1.2.2.dist-info/METADATA
astropandas-1.2.2.dist-info/WHEEL
astropandas-1.2.2.dist-info/top_level.txt
astropandas-1.2.2.dist-info/RECORD
