Metadata-Version: 2.1
Name: astropandas
Version: 1.2.2
Summary: Tools to expand on pandas functionality for astronomical operations.
Home-page: https://github.com/jlvdb/astropandas
Author-email: Jan Luca van den Busch <jlvdb@astro.ruhr-uni-bochum.de>
License: GPL-3.0-or-later
Classifier: Intended Audience :: Science/Research
Classifier: Topic :: Scientific/Engineering :: Astronomy
Classifier: Programming Language :: Python :: 3
Classifier: License :: OSI Approved :: GNU General Public License v3 or later (GPLv3+)
Requires-Python: >=3.7
License-File: LICENSE
Requires-Dist: numpy
Requires-Dist: pandas
Requires-Dist: scipy
Requires-Dist: fitsio
Provides-Extra: plot
Requires-Dist: matplotlib ; extra == 'plot'
